doenut/__init__.py
doenut/data/__init__.py
doenut/data/data_set.py
doenut/data/modifiable_data_set.py
doenut/data/modifiers/__init__.py
doenut/data/modifiers/column_selector.py
doenut/data/modifiers/data_set_modifier.py
doenut/data/modifiers/duplicate_averager.py
doenut/data/modifiers/duplicate_remover.py
doenut/data/modifiers/ortho_scaler.py
doenut/designer.py
doenut/doenut.py
doenut/models/__init__.py
doenut/models/averaged_model.py
doenut/models/averaged_model_set.py
doenut/models/model.py
doenut/models/model_set.py
doenut/plot.py
doenut-0.1.1.dist-info/LICENSE
doenut-0.1.1.dist-info/METADATA
doenut-0.1.1.dist-info/WHEEL
doenut-0.1.1.dist-info/RECORD
