Metadata-Version: 2.1
Name: doenut
Version: 0.1.1
Summary: Design Of Experiments Numerical Utility Toolkit
License: MIT
Author: Ella Gale
Requires-Python: >=3.9,<3.13
Classifier: License :: OSI Approved :: MIT License
Classifier: Programming Language :: Python :: 3
Classifier: Programming Language :: Python :: 3.9
Classifier: Programming Language :: Python :: 3.10
Classifier: Programming Language :: Python :: 3.11
Requires-Dist: doepy (>=0.0.1,<0.0.2)
Requires-Dist: matplotlib (>=3.8.1,<4.0.0)
Requires-Dist: numpy (>=1.26.1,<2.0.0)
Requires-Dist: pandas (>=2.1.2,<3.0.0)
Requires-Dist: scikit-learn (>=1.3.2,<2.0.0)
